mmm_fair/__init__.py
mmm_fair/data_process.py
mmm_fair/dataset.py
mmm_fair/dataset_visualization.py
mmm_fair/deploy_utils.py
mmm_fair/fairlearn_report.py
mmm_fair/hyperparams.py
mmm_fair/mammoth_csv.py
mmm_fair/mmm_fair.py
mmm_fair/mmm_fair_gb.py
mmm_fair/onnx_utils.py
mmm_fair/train_and_deploy.py
mmm_fair/viz_trade_offs.py
mmm_fair/mchat/__init__.py
mmm_fair/mchat/groq_utils.py
mmm_fair/mchat/langchain_utils.py
mmm_fair/mchat/mmm_app.py
mmm_fair/mchat/openai_utils.py
mmm_fair/mchat/together_utils.py
mmm_fair/mchat/untitled.py
mmm_fair/mchat/static/chat.css
mmm_fair/mchat/static/chat.js
mmm_fair/mchat/static/mmm-fair.png
mmm_fair/mchat/templates/index.html
mmm_fair-2.2.11.dist-info/licenses/LICENSE
mmm_fair-2.2.11.dist-info/METADATA
mmm_fair-2.2.11.dist-info/WHEEL
mmm_fair-2.2.11.dist-info/entry_points.txt
mmm_fair-2.2.11.dist-info/top_level.txt
mmm_fair-2.2.11.dist-info/RECORD
