Metadata-Version: 2.4
Name: mmm-fair
Version: 2.2.11
Summary: A multi-objective multi-fairness boosting classifier
Author-email: Arjun Roy <arjunroyihrpa@gmail.com>, Swati Swati <swati17293@gmail.com>, Emmanouil Panagiotou <panagiotouemm@gmail.com>
License:                                  Apache License
Project-URL: Homepage, https://github.com/arjunroyihrpa/MMM_fair
Project-URL: Bug Tracker, https://github.com/arjunroyihrpa/MMM_fair/issues
Keywords: fairness,boosting,classification,machine-learning
Requires-Python: >=3.11
License-File: LICENSE
Requires-Dist: numpy>=1.26.4
Requires-Dist: six>=1.16.0
Requires-Dist: pymoo>=0.6.1.3
Requires-Dist: scikit-learn>=1.5.2
Requires-Dist: ucimlrepo
Requires-Dist: pandas>=2.2.3
Requires-Dist: fairbench
Requires-Dist: skl2onnx==1.17.0
Requires-Dist: tqdm
Requires-Dist: plotly
Requires-Dist: onnxruntime
Requires-Dist: fairlearn
Requires-Dist: rich
Requires-Dist: Flask
Requires-Dist: Flask-Session
Provides-Extra: llm-gpt
Requires-Dist: openai; extra == "llm-gpt"
Requires-Dist: langchain>=0.1.14; extra == "llm-gpt"
Requires-Dist: langchain-community; extra == "llm-gpt"
Requires-Dist: bs4; extra == "llm-gpt"
Requires-Dist: python-dotenv; extra == "llm-gpt"
Provides-Extra: llm-groq
Requires-Dist: langchain-groq; extra == "llm-groq"
Requires-Dist: langchain>=0.1.14; extra == "llm-groq"
Requires-Dist: langchain-community; extra == "llm-groq"
Requires-Dist: bs4; extra == "llm-groq"
Requires-Dist: python-dotenv; extra == "llm-groq"
Provides-Extra: llm-together
Requires-Dist: langchain-together; extra == "llm-together"
Requires-Dist: langchain>=0.1.14; extra == "llm-together"
Requires-Dist: langchain-community; extra == "llm-together"
Requires-Dist: bs4; extra == "llm-together"
Requires-Dist: python-dotenv; extra == "llm-together"
Dynamic: license-file
